.DS_Store
django_page_slapper-1.3.dist-info/DESCRIPTION.rst
django_page_slapper-1.3.dist-info/METADATA
django_page_slapper-1.3.dist-info/RECORD
django_page_slapper-1.3.dist-info/WHEEL
django_page_slapper-1.3.dist-info/metadata.json
django_page_slapper-1.3.dist-info/top_level.txt
page/__init__.py
page/admin.py
page/apps.py
page/context.py
page/forms.py
page/middleware.py
page/models.py
page/rss.py
page/signals.py
page/sitemap.py
page/tests.py
page/urls.py
page/utils.py
page/views_editor.py
page/views_page.py
page/views_site.py
page/migrations/0001_initial.py
page/migrations/0002_page_version.py
page/migrations/0003_auto_20170624_2338.py
page/migrations/__init__.py
page/static/.DS_Store
page/static/page/uploader/cors/postmessage.html
page/static/page/uploader/cors/result.html
page/static/page/uploader/css/demo-ie8.css
page/static/page/uploader/css/demo.css
page/static/page/uploader/css/jquery.fileupload-noscript.css
page/static/page/uploader/css/jquery.fileupload-ui-noscript.css
page/static/page/uploader/css/jquery.fileupload-ui.css
page/static/page/uploader/css/jquery.fileupload.css
page/static/page/uploader/css/style.css
page/static/page/uploader/img/loading.gif
page/static/page/uploader/img/progressbar.gif
page/static/page/uploader/js/app.js
page/static/page/uploader/js/jquery.fileupload-angular.js
page/static/page/uploader/js/jquery.fileupload-audio.js
page/static/page/uploader/js/jquery.fileupload-image.js
page/static/page/uploader/js/jquery.fileupload-jquery-ui.js
page/static/page/uploader/js/jquery.fileupload-process.js
page/static/page/uploader/js/jquery.fileupload-ui.js
page/static/page/uploader/js/jquery.fileupload-validate.js
page/static/page/uploader/js/jquery.fileupload-video.js
page/static/page/uploader/js/jquery.fileupload.js
page/static/page/uploader/js/jquery.iframe-transport.js
page/static/page/uploader/js/main.js
page/static/page/uploader/js/cors/jquery.postmessage-transport.js
page/static/page/uploader/js/cors/jquery.xdr-transport.js
page/static/page/uploader/js/vendor/jquery.ui.widget.js
page/static/tinymce/.DS_Store
page/static/tinymce/LICENSE.TXT
page/static/tinymce/changelog.txt
page/static/tinymce/js/tinymce/jquery.tinymce.min.js
