Metadata-Version: 2.0
Name: django-page-slapper
Version: 1.3
Summary: A django page manager.
Home-page: https://bitbucket.org/queenorych/django-page-slapper
Author: Mike Dobbs
Author-email: mike.j.dobbs@gmail.com
License: UNKNOWN
Platform: UNKNOWN
Classifier: Environment :: Web Environment
Classifier: License :: OSI Approved :: BSD License
Classifier: Framework :: Django
Classifier: Programming Language :: Python
